<?xml version="1.0" encoding="utf-8"?>
<Defs>
  <SoundDef>
    <defName>Pawn_Female1_Wounded</defName>
    <context>MapOnly</context>
    <eventNames />
    <maxVoices>20</maxVoices>
    <subSounds>
      <li>
        <grains>
          <li Class="AudioGrain_Folder">
            <clipFolderPath>Pawn/Animal/Female1/Female1_Pain1</clipFolderPath>
          </li>
          <li Class="AudioGrain_Folder">
            <clipFolderPath>Pawn/Animal/Female1/Female1_Pain2</clipFolderPath>
          </li>
          <li Class="AudioGrain_Folder">
            <clipFolderPath>Pawn/Animal/Female1/Female1_Pain3</clipFolderPath>
          </li>
          <li Class="AudioGrain_Folder">
            <clipFolderPath>Pawn/Animal/Female1/Female1_Pain4</clipFolderPath>
          </li>
          <li Class="AudioGrain_Folder">
            <clipFolderPath>Pawn/Animal/Female1/Female1_Pain5</clipFolderPath>
          </li>
          <li Class="AudioGrain_Folder">
            <clipFolderPath>Pawn/Animal/Female1/Female1_Pain6</clipFolderPath>
          </li>
          <li Class="AudioGrain_Folder">
            <clipFolderPath>Pawn/Animal/Female1/Female1_Pain7</clipFolderPath>
          </li>
          <li Class="AudioGrain_Folder">
            <clipFolderPath>Pawn/Animal/Female1/Female1_Pain8</clipFolderPath>
          </li>
          <li Class="AudioGrain_Folder">
            <clipFolderPath>Pawn/Animal/Female1/Female1_Pain9</clipFolderPath>
          </li>
          <li Class="AudioGrain_Folder">
            <clipFolderPath>Pawn/Animal/Female1/Female1_Pain10</clipFolderPath>
          </li>
          <li Class="AudioGrain_Folder">
            <clipFolderPath>Pawn/Animal/Female1/Female1_Pain11</clipFolderPath>
          </li>
          <li Class="AudioGrain_Folder">
            <clipFolderPath>Pawn/Animal/Female1/Female1_Pain12</clipFolderPath>
          </li>
          <li Class="AudioGrain_Folder">
            <clipFolderPath>Pawn/Animal/Female1/Female1_Pain13</clipFolderPath>
          </li>
          <li Class="AudioGrain_Folder">
            <clipFolderPath>Pawn/Animal/Female1/Female1_Pain14</clipFolderPath>
          </li>
          <li Class="AudioGrain_Folder">
            <clipFolderPath>Pawn/Animal/Female1/Female1_Pain15</clipFolderPath>
          </li>
          <li Class="AudioGrain_Folder">
            <clipFolderPath>Pawn/Animal/Female1/Female1_Pain16</clipFolderPath>
          </li>
          <li Class="AudioGrain_Folder">
            <clipFolderPath>Pawn/Animal/Female1/Female1_Pain17</clipFolderPath>
          </li>
          <li Class="AudioGrain_Folder">
            <clipFolderPath>Pawn/Animal/Female1/Female1_Pain18</clipFolderPath>
          </li>
          <li Class="AudioGrain_Folder">
            <clipFolderPath>Pawn/Animal/Female1/Female1_Pain19</clipFolderPath>
          </li>
          <li Class="AudioGrain_Folder">
            <clipFolderPath>Pawn/Animal/Female1/Female1_Pain20</clipFolderPath>
          </li>
          <li Class="AudioGrain_Folder">
            <clipFolderPath>Pawn/Animal/Female1/Female1_Pain21</clipFolderPath>
          </li>
          <li Class="AudioGrain_Folder">
            <clipFolderPath>Pawn/Animal/Female1/Female1_Pain22</clipFolderPath>
          </li>
          <li Class="AudioGrain_Folder">
            <clipFolderPath>Pawn/Animal/Female1/Female1_Pain23</clipFolderPath>
          </li>
          <li Class="AudioGrain_Folder">
            <clipFolderPath>Pawn/Animal/Female1/Female1_Pain24</clipFolderPath>
          </li>
        </grains>
        <volumeRange>
          <min>45</min>
          <max>50</max>
        </volumeRange>
        <pitchRange>
          <min>0.9</min>
          <max>1.0</max>
        </pitchRange>
        <distRange>
          <min>0</min>
          <max>30</max>
        </distRange>
        <repeatMode>NeverTwice</repeatMode>
        <sustainLoop>False</sustainLoop>
      </li>
    </subSounds>
  </SoundDef>
  <SoundDef>
    <defName>Pawn_Female1_Death</defName>
    <context>MapOnly</context>
    <eventNames />
    <maxVoices>24</maxVoices>
    <subSounds>
      <li>
        <grains>
          <li Class="AudioGrain_Folder">
            <clipFolderPath>Pawn/Animal/Female1/Female1_Death1</clipFolderPath>
          </li>
          <li Class="AudioGrain_Folder">
            <clipFolderPath>Pawn/Animal/Female1/Female1_Death2</clipFolderPath>
          </li>
          <li Class="AudioGrain_Folder">
            <clipFolderPath>Pawn/Animal/Female1/Female1_Death3</clipFolderPath>
          </li>
          <li Class="AudioGrain_Folder">
            <clipFolderPath>Pawn/Animal/Female1/Female1_Death4</clipFolderPath>
          </li>
          <li Class="AudioGrain_Folder">
            <clipFolderPath>Pawn/Animal/Female1/Female1_Death5</clipFolderPath>
          </li>
          <li Class="AudioGrain_Folder">
            <clipFolderPath>Pawn/Animal/Female1/Female1_Death6</clipFolderPath>
          </li>
          <li Class="AudioGrain_Folder">
            <clipFolderPath>Pawn/Animal/Female1/Female1_Death7</clipFolderPath>
          </li>
          <li Class="AudioGrain_Folder">
            <clipFolderPath>Pawn/Animal/Female1/Female1_Death8</clipFolderPath>
          </li>
          <li Class="AudioGrain_Folder">
            <clipFolderPath>Pawn/Animal/Female1/Female1_Death9</clipFolderPath>
          </li>
          <li Class="AudioGrain_Folder">
            <clipFolderPath>Pawn/Animal/Female1/Female1_Death10</clipFolderPath>
          </li>
          <li Class="AudioGrain_Folder">
            <clipFolderPath>Pawn/Animal/Female1/Female1_Death11</clipFolderPath>
          </li>
          <li Class="AudioGrain_Folder">
            <clipFolderPath>Pawn/Animal/Female1/Female1_Death14</clipFolderPath>
          </li>
          <li Class="AudioGrain_Folder">
            <clipFolderPath>Pawn/Animal/Female1/Female1_Death18</clipFolderPath>
          </li>
          <li Class="AudioGrain_Folder">
            <clipFolderPath>Pawn/Animal/Female1/Female1_Death19</clipFolderPath>
          </li>
          <li Class="AudioGrain_Folder">
            <clipFolderPath>Pawn/Animal/Female1/Female1_Death20</clipFolderPath>
          </li>
          <li Class="AudioGrain_Folder">
            <clipFolderPath>Pawn/Animal/Female1/Female1_Death21</clipFolderPath>
          </li>
          <li Class="AudioGrain_Folder">
            <clipFolderPath>Pawn/Animal/Female1/Female1_Death22</clipFolderPath>
          </li>
          <li Class="AudioGrain_Folder">
            <clipFolderPath>Pawn/Animal/Female1/Female1_Death23</clipFolderPath>
          </li>
          <li Class="AudioGrain_Folder">
            <clipFolderPath>Pawn/Animal/Female1/Female1_Death24</clipFolderPath>
          </li>
          <li Class="AudioGrain_Folder">
            <clipFolderPath>Pawn/Animal/Female1/Female1_Death25</clipFolderPath>
          </li>
          <li Class="AudioGrain_Folder">
            <clipFolderPath>Pawn/Animal/Female1/Female1_Death26</clipFolderPath>
          </li>
          <li Class="AudioGrain_Folder">
            <clipFolderPath>Pawn/Animal/Female1/Female1_Death27</clipFolderPath>
          </li>
          <li Class="AudioGrain_Folder">
            <clipFolderPath>Pawn/Animal/Female1/Female1_Death28</clipFolderPath>
          </li>
          <li Class="AudioGrain_Folder">
            <clipFolderPath>Pawn/Animal/Female1/Female1_Death29</clipFolderPath>
          </li>
        </grains>
        <volumeRange>
          <min>63</min>
          <max>63</max>
        </volumeRange>
        <pitchRange>
          <min>0.9</min>
          <max>1.1</max>
        </pitchRange>
        <distRange>
          <min>0</min>
          <max>50</max>
        </distRange>
        <sustainLoop>False</sustainLoop>
      </li>
    </subSounds>
  </SoundDef>
  <SoundDef>
    <defName>Pawn_Female2_Wounded</defName>
    <context>MapOnly</context>
    <eventNames />
    <maxVoices>20</maxVoices>
    <subSounds>
      <li>
        <grains>
          <li Class="AudioGrain_Folder">
            <clipFolderPath>Pawn/Animal/Female2/Female2_Pain1</clipFolderPath>
          </li>
          <li Class="AudioGrain_Folder">
            <clipFolderPath>Pawn/Animal/Female2/Female2_Pain2</clipFolderPath>
          </li>
          <li Class="AudioGrain_Folder">
            <clipFolderPath>Pawn/Animal/Female2/Female2_Pain3</clipFolderPath>
          </li>
          <li Class="AudioGrain_Folder">
            <clipFolderPath>Pawn/Animal/Female2/Female2_Pain4</clipFolderPath>
          </li>
          <li Class="AudioGrain_Folder">
            <clipFolderPath>Pawn/Animal/Female2/Female2_Pain5</clipFolderPath>
          </li>
          <li Class="AudioGrain_Folder">
            <clipFolderPath>Pawn/Animal/Female2/Female2_Pain6</clipFolderPath>
          </li>
          <li Class="AudioGrain_Folder">
            <clipFolderPath>Pawn/Animal/Female2/Female2_Pain7</clipFolderPath>
          </li>
          <li Class="AudioGrain_Folder">
            <clipFolderPath>Pawn/Animal/Female2/Female2_Pain8</clipFolderPath>
          </li>
          <li Class="AudioGrain_Folder">
            <clipFolderPath>Pawn/Animal/Female2/Female2_Pain9</clipFolderPath>
          </li>
          <li Class="AudioGrain_Folder">
            <clipFolderPath>Pawn/Animal/Female2/Female2_Pain10</clipFolderPath>
          </li>
          <li Class="AudioGrain_Folder">
            <clipFolderPath>Pawn/Animal/Female2/Female2_Pain11</clipFolderPath>
          </li>
          <li Class="AudioGrain_Folder">
            <clipFolderPath>Pawn/Animal/Female2/Female2_Pain12</clipFolderPath>
          </li>
          <li Class="AudioGrain_Folder">
            <clipFolderPath>Pawn/Animal/Female2/Female2_Pain13</clipFolderPath>
          </li>
          <li Class="AudioGrain_Folder">
            <clipFolderPath>Pawn/Animal/Female2/Female2_Pain14</clipFolderPath>
          </li>
          <li Class="AudioGrain_Folder">
            <clipFolderPath>Pawn/Animal/Female2/Female2_Pain15</clipFolderPath>
          </li>
          <li Class="AudioGrain_Folder">
            <clipFolderPath>Pawn/Animal/Female2/Female2_Pain16</clipFolderPath>
          </li>
          <li Class="AudioGrain_Folder">
            <clipFolderPath>Pawn/Animal/Female2/Female2_Pain17</clipFolderPath>
          </li>
          <li Class="AudioGrain_Folder">
            <clipFolderPath>Pawn/Animal/Female2/Female2_Pain18</clipFolderPath>
          </li>
          <li Class="AudioGrain_Folder">
            <clipFolderPath>Pawn/Animal/Female2/Female2_Pain19</clipFolderPath>
          </li>
          <li Class="AudioGrain_Folder">
            <clipFolderPath>Pawn/Animal/Female2/Female2_Pain20</clipFolderPath>
          </li>
          <li Class="AudioGrain_Folder">
            <clipFolderPath>Pawn/Animal/Female2/Female2_Pain21</clipFolderPath>
          </li>
          <li Class="AudioGrain_Folder">
            <clipFolderPath>Pawn/Animal/Female2/Female2_Pain22</clipFolderPath>
          </li>
          <li Class="AudioGrain_Folder">
            <clipFolderPath>Pawn/Animal/Female2/Female2_Pain23</clipFolderPath>
          </li>
          <li Class="AudioGrain_Folder">
            <clipFolderPath>Pawn/Animal/Female2/Female2_Pain24</clipFolderPath>
          </li>
        </grains>
        <volumeRange>
          <min>45</min>
          <max>50</max>
        </volumeRange>
        <pitchRange>
          <min>0.9</min>
          <max>1.0</max>
        </pitchRange>
        <distRange>
          <min>0</min>
          <max>30</max>
        </distRange>
        <repeatMode>NeverTwice</repeatMode>
        <sustainLoop>False</sustainLoop>
      </li>
    </subSounds>
  </SoundDef>
  <SoundDef>
    <defName>Pawn_Female2_Death</defName>
    <context>MapOnly</context>
    <eventNames />
    <maxVoices>24</maxVoices>
    <subSounds>
      <li>
        <grains>
          <li Class="AudioGrain_Folder">
            <clipFolderPath>Pawn/Animal/Female2/Female2_Death1</clipFolderPath>
          </li>
          <li Class="AudioGrain_Folder">
            <clipFolderPath>Pawn/Animal/Female2/Female2_Death2</clipFolderPath>
          </li>
          <li Class="AudioGrain_Folder">
            <clipFolderPath>Pawn/Animal/Female2/Female2_Death3</clipFolderPath>
          </li>
          <li Class="AudioGrain_Folder">
            <clipFolderPath>Pawn/Animal/Female2/Female2_Death4</clipFolderPath>
          </li>
          <li Class="AudioGrain_Folder">
            <clipFolderPath>Pawn/Animal/Female2/Female2_Death5</clipFolderPath>
          </li>
          <li Class="AudioGrain_Folder">
            <clipFolderPath>Pawn/Animal/Female2/Female2_Death6</clipFolderPath>
          </li>
          <li Class="AudioGrain_Folder">
            <clipFolderPath>Pawn/Animal/Female2/Female2_Death7</clipFolderPath>
          </li>
          <li Class="AudioGrain_Folder">
            <clipFolderPath>Pawn/Animal/Female2/Female2_Death8</clipFolderPath>
          </li>
          <li Class="AudioGrain_Folder">
            <clipFolderPath>Pawn/Animal/Female2/Female2_Death9</clipFolderPath>
          </li>
          <li Class="AudioGrain_Folder">
            <clipFolderPath>Pawn/Animal/Female2/Female2_Death10</clipFolderPath>
          </li>
          <li Class="AudioGrain_Folder">
            <clipFolderPath>Pawn/Animal/Female2/Female2_Death11</clipFolderPath>
          </li>
          <li Class="AudioGrain_Folder">
            <clipFolderPath>Pawn/Animal/Female2/Female2_Death14</clipFolderPath>
          </li>
          <li Class="AudioGrain_Folder">
            <clipFolderPath>Pawn/Animal/Female2/Female2_Death18</clipFolderPath>
          </li>
          <li Class="AudioGrain_Folder">
            <clipFolderPath>Pawn/Animal/Female2/Female2_Death19</clipFolderPath>
          </li>
          <li Class="AudioGrain_Folder">
            <clipFolderPath>Pawn/Animal/Female2/Female2_Death20</clipFolderPath>
          </li>
          <li Class="AudioGrain_Folder">
            <clipFolderPath>Pawn/Animal/Female2/Female2_Death21</clipFolderPath>
          </li>
          <li Class="AudioGrain_Folder">
            <clipFolderPath>Pawn/Animal/Female2/Female2_Death22</clipFolderPath>
          </li>
          <li Class="AudioGrain_Folder">
            <clipFolderPath>Pawn/Animal/Female2/Female2_Death23</clipFolderPath>
          </li>
          <li Class="AudioGrain_Folder">
            <clipFolderPath>Pawn/Animal/Female2/Female2_Death24</clipFolderPath>
          </li>
          <li Class="AudioGrain_Folder">
            <clipFolderPath>Pawn/Animal/Female2/Female2_Death25</clipFolderPath>
          </li>
          <li Class="AudioGrain_Folder">
            <clipFolderPath>Pawn/Animal/Female2/Female2_Death26</clipFolderPath>
          </li>
          <li Class="AudioGrain_Folder">
            <clipFolderPath>Pawn/Animal/Female2/Female2_Death27</clipFolderPath>
          </li>
          <li Class="AudioGrain_Folder">
            <clipFolderPath>Pawn/Animal/Female2/Female2_Death28</clipFolderPath>
          </li>
          <li Class="AudioGrain_Folder">
            <clipFolderPath>Pawn/Animal/Female2/Female2_Death29</clipFolderPath>
          </li>
        </grains>
        <volumeRange>
          <min>63</min>
          <max>63</max>
        </volumeRange>
        <pitchRange>
          <min>0.9</min>
          <max>1.1</max>
        </pitchRange>
        <distRange>
          <min>0</min>
          <max>50</max>
        </distRange>
        <sustainLoop>False</sustainLoop>
      </li>
    </subSounds>
  </SoundDef>
</Defs>